{
  "parent": "minecraft:block/block",
  "loader": "gtceu:machine",
  "machine": "gregecore:pressure_input_machine",
  "replaceable_textures": [
    "bottom",
    "top",
    "side"
  ],
  "variants": {
    "is_formed=false,is_painted=false": {
      "model": {
        "parent": "gtceu:block/machine/template/part/hatch_machine",
        "textures": {
          "bottom": "gtceu:block/casings/voltage/lv/bottom",
          "overlay": "gregecore:block/overlay/coolant_input/overlay_front",
          "side": "gtceu:block/casings/voltage/lv/side",
          "top": "gtceu:block/casings/voltage/lv/top"
        }
      }
    },
    "is_formed=false,is_painted=true": {
      "model": {
        "parent": "gtceu:block/machine/template/part/hatch_machine_color_ring",
        "textures": {
          "bottom": "gtceu:block/casings/voltage/lv/bottom",
          "overlay": "gregecore:block/overlay/coolant_input/overlay_front",
          "side": "gtceu:block/casings/voltage/lv/side",
          "top": "gtceu:block/casings/voltage/lv/top"
        }
      }
    },
    "is_formed=true,is_painted=false": {
      "model": {
        "parent": "gtceu:block/machine/template/part/hatch_machine",
        "textures": {
          "bottom": "gtceu:block/casings/voltage/lv/bottom",
          "overlay": "gregecore:block/overlay/coolant_input/overlay_front",
          "side": "gtceu:block/casings/voltage/lv/side",
          "top": "gtceu:block/casings/voltage/lv/top"
        }
      }
    },
    "is_formed=true,is_painted=true": {
      "model": {
        "parent": "gtceu:block/machine/template/part/hatch_machine_color_ring",
        "textures": {
          "bottom": "gtceu:block/casings/voltage/lv/bottom",
          "overlay": "gregecore:block/overlay/coolant_input/overlay_front",
          "side": "gtceu:block/casings/voltage/lv/side",
          "top": "gtceu:block/casings/voltage/lv/top"
        }
      }
    }
  }
}